{
  "overall": {
    "total_success_rate": 0.0,
    "total_episodes": 50,
    "total_successes": 0
  },
  "config": {
    "benchmark": "libero-plus",
    "task_suite": "libero_goal",
    "nfe": 1,
    "max_tasks": 10,
    "task_offset": 0,
    "replan_steps": 5,
    "num_steps_wait": 10,
    "seed": 7,
    "checkpoint_path": "/root/autodl-tmp/freeflow/checkpoints/finetuned/freeflow/step_15000",
    "action_horizon": 10
  },
  "per_task": {
    "open_the_middle_drawer_of_the_cabinet_table_1.bddl": {
      "task_id": 0,
      "task_name": "open_the_middle_drawer_of_the_cabinet_table_1.bddl",
      "task_description": "open the middle drawer of the cabinet table 1",
      "perturb_info": {
        "base_suite": "open"
      },
      "successes": 0,
      "episodes": 5,
      "rate": 0.0
    },
    "open_the_middle_drawer_of_the_cabinet_table_10.bddl": {
      "task_id": 1,
      "task_name": "open_the_middle_drawer_of_the_cabinet_table_10.bddl",
      "task_description": "open the middle drawer of the cabinet table 10",
      "perturb_info": {
        "base_suite": "open"
      },
      "successes": 0,
      "episodes": 5,
      "rate": 0.0
    },
    "open_the_middle_drawer_of_the_cabinet_table_12.bddl": {
      "task_id": 2,
      "task_name": "open_the_middle_drawer_of_the_cabinet_table_12.bddl",
      "task_description": "open the middle drawer of the cabinet table 12",
      "perturb_info": {
        "base_suite": "open"
      },
      "successes": 0,
      "episodes": 5,
      "rate": 0.0
    },
    "open_the_middle_drawer_of_the_cabinet_table_13.bddl": {
      "task_id": 3,
      "task_name": "open_the_middle_drawer_of_the_cabinet_table_13.bddl",
      "task_description": "open the middle drawer of the cabinet table 13",
      "perturb_info": {
        "base_suite": "open"
      },
      "successes": 0,
      "episodes": 5,
      "rate": 0.0
    },
    "open_the_middle_drawer_of_the_cabinet_table_15.bddl": {
      "task_id": 4,
      "task_name": "open_the_middle_drawer_of_the_cabinet_table_15.bddl",
      "task_description": "open the middle drawer of the cabinet table 15",
      "perturb_info": {
        "base_suite": "open"
      },
      "successes": 0,
      "episodes": 5,
      "rate": 0.0
    },
    "open_the_middle_drawer_of_the_cabinet_table_16.bddl": {
      "task_id": 5,
      "task_name": "open_the_middle_drawer_of_the_cabinet_table_16.bddl",
      "task_description": "open the middle drawer of the cabinet table 16",
      "perturb_info": {
        "base_suite": "open"
      },
      "successes": 0,
      "episodes": 5,
      "rate": 0.0
    },
    "open_the_middle_drawer_of_the_cabinet_table_17.bddl": {
      "task_id": 6,
      "task_name": "open_the_middle_drawer_of_the_cabinet_table_17.bddl",
      "task_description": "open the middle drawer of the cabinet table 17",
      "perturb_info": {
        "base_suite": "open"
      },
      "successes": 0,
      "episodes": 5,
      "rate": 0.0
    },
    "open_the_middle_drawer_of_the_cabinet_table_18.bddl": {
      "task_id": 7,
      "task_name": "open_the_middle_drawer_of_the_cabinet_table_18.bddl",
      "task_description": "open the middle drawer of the cabinet table 18",
      "perturb_info": {
        "base_suite": "open"
      },
      "successes": 0,
      "episodes": 5,
      "rate": 0.0
    },
    "open_the_middle_drawer_of_the_cabinet_table_19.bddl": {
      "task_id": 8,
      "task_name": "open_the_middle_drawer_of_the_cabinet_table_19.bddl",
      "task_description": "open the middle drawer of the cabinet table 19",
      "perturb_info": {
        "base_suite": "open"
      },
      "successes": 0,
      "episodes": 5,
      "rate": 0.0
    },
    "open_the_middle_drawer_of_the_cabinet_table_2.bddl": {
      "task_id": 9,
      "task_name": "open_the_middle_drawer_of_the_cabinet_table_2.bddl",
      "task_description": "open the middle drawer of the cabinet table 2",
      "perturb_info": {
        "base_suite": "open"
      },
      "successes": 0,
      "episodes": 5,
      "rate": 0.0
    }
  },
  "timing": {
    "all_latencies_ms": [
      39.39,
      38.58,
      38.66,
      39.56,
      39.13,
      39.36,
      39.3,
      38.62,
      38.64,
      38.91,
      38.99,
      39.38,
      39.79,
      39.23,
      39.54,
      39.47,
      38.56,
      38.85,
      38.87,
      38.94,
      39.23,
      40.22,
      39.22,
      39.26,
      39.2,
      38.73,
      38.44,
      38.42,
      37.8,
      37.72,
      38.26,
      37.85,
      38.3,
      39.08,
      38.12,
      38.42,
      38.01,
      37.75,
      38.27,
      37.75,
      38.59,
      37.43,
      39.32,
      38.35,
      37.74,
      38.32,
      37.77,
      39.11,
      38.73,
      37.77,
      37.69,
      38.11,
      38.08,
      38.37,
      37.73,
      38.43,
      38.45,
      37.76,
      37.76,
      37.64,
      39.16,
      38.21,
      38.36,
      38.15,
      38.18,
      37.89,
      37.69,
      37.96,
      37.83,
      37.64,
      38.72,
      38.2,
      37.81,
      37.63,
      38.59,
      38.83,
      38.64,
      38.72,
      38.41,
      38.77,
      38.61,
      38.89,
      38.86,
      38.91,
      38.87,
      38.41,
      38.68,
      38.33,
      38.32,
      37.9,
      39.71,
      39.28,
      39.79,
      39.03,
      38.55,
      39.17,
      39.98,
      39.49,
      38.78,
      39.07,
      39.34,
      39.58,
      38.56,
      39.63,
      38.73,
      39.85,
      39.42,
      39.06,
      39.1,
      38.82,
      40.09,
      39.49,
      39.25,
      38.88,
      38.81,
      39.5,
      39.81,
      38.96,
      39.31,
      40.32,
      40.44,
      39.4,
      38.92,
      39.58,
      39.1,
      39.35,
      38.93,
      39.01,
      39.21,
      39.6,
      39.61,
      39.8,
      39.02,
      39.22,
      38.57,
      38.48,
      38.49,
      38.6,
      38.84,
      39.07,
      39.41,
      38.78,
      39.87,
      38.57,
      39.07,
      39.42,
      38.56,
      38.51,
      38.73,
      39.81,
      39.43,
      39.21,
      39.29,
      39.71,
      39.34,
      38.93,
      38.89,
      39.66,
      39.51,
      39.71,
      38.63,
      39.04,
      39.38,
      39.53,
      38.82,
      38.59,
      39.62,
      38.95,
      39.31,
      38.55,
      38.61,
      38.77,
      38.7,
      38.68,
      38.48,
      38.4,
      38.78,
      40.35,
      39.68,
      39.04,
      40.4,
      39.22,
      38.88,
      40.65,
      39.34,
      39.79,
      39.27,
      39.2,
      39.23,
      39.34,
      39.64,
      38.77,
      39.23,
      39.53,
      39.98,
      39.35,
      39.28,
      39.04,
      38.91,
      39.7,
      39.24,
      39.65,
      38.55,
      38.75,
      38.97,
      39.2,
      39.2,
      38.98,
      39.06,
      38.83,
      39.1,
      39.16,
      39.42,
      39.69,
      39.27,
      39.17,
      39.11,
      38.89,
      39.2,
      38.96,
      39.53,
      39.64,
      38.94,
      39.15,
      39.28,
      39.72,
      39.42,
      39.79,
      39.51,
      39.56,
      40.02,
      40.16,
      39.59,
      39.07,
      39.48,
      39.04,
      39.28,
      39.48,
      39.62,
      39.72,
      40.02,
      39.32,
      38.96,
      39.65,
      39.13,
      39.44,
      39.4,
      39.38,
      39.44,
      39.53,
      39.44,
      39.58,
      40.21,
      39.35,
      39.03,
      40.27,
      38.86,
      39.06,
      39.33,
      38.97,
      39.32,
      39.6,
      39.32,
      39.73,
      39.16,
      40.33,
      38.62,
      38.87,
      39.12,
      38.49,
      39.57,
      39.15,
      39.59,
      39.0,
      39.25,
      39.28,
      38.38,
      38.65,
      39.64,
      39.18,
      38.87,
      40.05,
      38.83,
      38.94,
      39.06,
      39.07,
      38.6,
      38.78,
      39.2,
      38.31,
      38.34,
      38.61,
      38.77,
      39.11,
      38.0,
      38.23,
      38.7,
      38.23,
      38.1,
      38.02,
      39.42,
      38.32,
      37.85,
      38.27,
      37.94,
      37.75,
      38.58,
      40.2,
      38.79,
      42.22,
      41.73,
      47.06,
      43.25,
      40.16,
      39.24,
      38.81,
      39.81,
      39.68,
      40.18,
      46.67,
      46.79,
      41.59,
      45.68,
      45.03,
      40.4,
      38.21,
      38.26,
      37.92,
      37.5,
      38.3,
      38.35,
      37.9,
      38.27,
      37.81,
      37.97,
      39.19,
      38.3,
      38.25,
      37.86,
      37.77,
      38.05,
      38.26,
      37.87,
      38.38,
      38.21,
      38.61,
      39.96,
      38.37,
      38.36,
      38.03,
      37.88,
      39.11,
      39.1,
      37.9,
      37.95,
      38.59,
      37.99,
      37.64,
      37.52,
      37.72,
      39.36,
      39.04,
      38.59,
      39.06,
      39.44,
      38.39,
      38.94,
      39.52,
      39.21,
      39.86,
      38.87,
      39.68,
      39.21,
      39.44,
      39.32,
      38.84,
      38.38,
      39.1,
      39.44,
      38.5,
      38.41,
      38.56,
      38.7,
      39.03,
      38.34,
      38.63,
      38.42,
      38.22,
      38.01,
      38.35,
      38.47,
      38.57,
      38.34,
      38.84,
      38.65,
      38.62,
      38.01,
      38.38,
      40.71,
      38.39,
      38.28,
      38.93,
      39.29,
      39.36,
      39.26,
      38.82,
      38.89,
      39.25,
      38.31,
      37.92,
      38.18,
      38.2,
      38.86,
      39.08,
      39.71,
      39.89,
      38.84,
      38.69,
      38.61,
      38.31,
      39.41,
      38.55,
      37.99,
      38.02,
      37.68,
      37.6,
      38.25,
      38.21,
      38.37,
      38.22,
      38.93,
      38.37,
      39.09,
      39.8,
      38.46,
      38.17,
      38.89,
      39.43,
      39.17,
      39.06,
      39.27,
      38.46,
      38.86,
      39.21,
      39.29,
      39.24,
      38.6,
      39.51,
      38.62,
      38.8,
      38.72,
      38.28,
      38.09,
      38.81,
      38.46,
      39.0,
      38.65,
      39.31,
      39.33,
      39.17,
      38.71,
      38.86,
      38.5,
      37.72,
      38.2,
      38.58,
      39.37,
      38.26,
      38.95,
      38.63,
      39.05,
      39.34,
      38.7,
      39.3,
      39.64,
      39.48,
      39.09,
      39.07,
      39.02,
      39.49,
      40.77,
      41.66,
      39.69,
      40.1,
      40.01,
      39.87,
      38.47,
      37.95,
      38.67,
      38.46,
      38.66,
      38.66,
      37.84,
      38.9,
      38.64,
      39.25,
      38.93,
      38.23,
      38.29,
      38.72,
      38.6,
      38.16,
      37.98,
      38.24,
      39.18,
      38.5,
      37.83,
      38.4,
      38.49,
      37.79,
      37.91,
      37.72,
      38.55,
      38.47,
      39.6,
      41.49,
      38.56,
      37.89,
      38.7,
      38.21,
      38.56,
      38.51,
      38.42,
      39.16,
      38.82,
      38.9,
      38.0,
      38.7,
      38.88,
      38.19,
      38.1,
      38.56,
      38.47,
      38.05,
      38.39,
      38.35,
      38.64,
      38.23,
      38.58,
      38.65,
      40.07,
      39.31,
      40.1,
      39.89,
      39.38,
      38.81,
      39.01,
      39.22,
      41.69,
      39.31,
      38.13,
      38.51,
      39.31,
      38.73,
      38.49,
      38.03,
      38.77,
      37.76,
      38.33,
      38.77,
      38.18,
      38.7,
      38.32,
      37.99,
      37.76,
      37.88,
      39.06,
      37.95,
      38.21,
      37.84,
      37.98,
      37.93,
      38.01,
      37.77,
      38.13,
      38.6,
      38.04,
      37.56,
      38.07,
      37.86,
      38.58,
      38.0,
      37.91,
      37.91,
      37.91,
      39.23,
      38.2,
      37.61,
      37.94,
      38.72,
      38.1,
      38.33,
      38.34,
      38.16,
      38.59,
      38.78,
      38.58,
      37.88,
      37.63,
      37.83,
      39.04,
      38.91,
      38.14,
      39.74,
      38.57,
      38.5,
      38.32,
      37.62,
      38.58,
      37.73,
      37.88,
      38.53,
      38.0,
      38.35,
      37.92,
      38.39,
      38.15,
      38.56,
      38.31,
      38.15,
      38.6,
      38.67,
      38.31,
      37.53,
      37.86,
      38.37,
      38.43,
      37.94,
      37.73,
      37.89,
      38.76,
      38.24,
      38.26,
      38.25,
      38.51,
      38.19,
      38.63,
      39.52,
      39.07,
      38.89,
      39.03,
      39.26,
      38.75,
      38.76,
      39.05,
      39.35,
      39.11,
      39.13,
      38.36,
      38.84,
      38.71,
      38.2,
      37.69,
      37.78,
      38.4,
      37.99,
      38.4,
      39.52,
      38.82,
      38.85,
      39.59,
      39.11,
      39.23,
      39.85,
      38.94,
      39.07,
      38.93,
      40.04,
      39.59,
      38.99,
      38.64,
      38.84,
      39.05,
      39.21,
      39.44,
      39.03,
      39.52,
      41.12,
      40.39,
      39.87,
      39.53,
      39.14,
      38.4,
      40.51,
      38.49,
      39.04,
      40.2,
      38.9,
      39.7,
      38.95,
      38.83,
      38.91,
      41.81,
      39.18,
      38.96,
      38.77,
      40.49,
      39.42,
      40.05,
      39.1,
      39.61,
      39.76,
      39.6,
      39.07,
      40.71,
      40.02,
      39.1,
      40.01,
      40.44,
      39.64,
      39.3,
      39.61,
      39.16,
      40.21,
      39.67,
      39.23,
      39.31,
      38.94,
      38.62,
      38.73,
      41.31,
      41.82,
      40.05,
      39.35,
      39.83,
      39.07,
      39.24,
      38.97,
      39.18,
      39.82,
      39.03,
      39.57,
      39.28,
      39.1,
      39.91,
      39.22,
      38.75,
      39.8,
      38.86,
      42.59,
      38.42,
      38.35,
      38.53,
      42.81,
      39.56,
      38.72,
      39.87,
      38.85,
      39.35,
      38.99,
      38.86,
      39.17,
      38.63,
      38.27,
      38.9,
      38.75,
      38.82,
      38.61,
      38.77,
      38.59,
      38.27,
      38.86,
      38.71,
      38.77,
      45.64,
      38.85,
      38.57,
      38.35,
      38.88,
      38.82,
      38.38,
      38.07,
      38.43,
      38.45,
      38.41,
      39.0,
      38.84,
      38.78,
      38.94,
      39.53,
      40.19,
      39.41,
      39.17,
      38.81,
      38.39,
      38.37,
      38.08,
      39.29,
      39.6,
      39.53,
      39.38,
      40.03,
      39.22,
      39.22,
      39.64,
      38.77,
      38.55,
      39.39,
      39.0,
      39.42,
      39.28,
      39.45,
      39.05,
      39.26,
      39.3,
      38.78,
      38.61,
      39.89,
      39.69,
      38.86,
      39.44,
      39.3,
      38.78,
      39.27,
      39.36,
      39.51,
      39.78,
      40.49,
      39.9,
      39.09,
      39.52,
      39.78,
      38.58,
      39.26,
      39.64,
      39.04,
      39.1,
      38.85,
      39.41,
      39.42,
      39.11,
      38.32,
      39.37,
      40.19,
      39.73,
      38.98,
      39.34,
      39.46,
      39.2,
      39.07,
      40.49,
      39.35,
      39.13,
      39.21,
      38.56,
      39.45,
      38.97,
      39.71,
      38.67,
      39.81,
      39.48,
      39.14,
      39.07,
      38.7,
      38.85,
      39.01,
      39.31,
      39.6,
      39.05,
      39.22,
      39.36,
      38.82,
      38.87,
      39.07,
      39.0,
      38.85,
      39.11,
      39.84,
      39.71,
      39.22,
      39.46,
      39.46,
      39.08,
      39.83,
      39.55,
      39.38,
      39.95,
      39.32,
      38.82,
      38.59,
      39.35,
      39.31,
      38.92,
      39.27,
      39.15,
      39.06,
      39.63,
      40.32,
      39.31,
      40.59,
      38.57,
      38.4,
      38.67,
      39.09,
      38.87,
      38.15,
      39.52,
      38.91,
      39.16,
      39.28,
      38.94,
      39.38,
      39.23,
      39.95,
      39.76,
      40.53,
      39.87,
      46.24,
      48.1,
      39.45,
      42.65,
      39.54,
      39.28,
      39.4,
      39.56,
      39.63,
      39.12,
      39.3,
      39.6,
      39.37,
      38.95,
      38.66,
      41.4,
      39.07,
      39.34,
      39.02,
      39.1,
      39.61,
      39.82,
      38.75,
      39.23,
      39.4,
      38.92,
      38.8,
      38.61,
      39.26,
      39.16,
      38.6,
      39.7,
      38.98,
      39.38,
      40.14,
      39.47,
      39.1,
      39.51,
      39.71,
      39.42,
      40.1,
      39.05,
      38.98,
      39.66,
      41.86,
      40.3,
      39.93,
      39.35,
      39.73,
      38.84,
      39.17,
      39.03,
      39.1,
      39.12,
      38.46,
      38.56,
      38.83,
      38.25,
      38.16,
      38.02,
      38.27,
      39.44,
      38.33,
      39.01,
      38.67,
      38.98,
      38.11,
      38.24,
      38.84,
      38.61,
      39.12,
      38.91,
      38.42,
      38.29,
      37.9,
      38.53,
      38.11,
      38.82,
      39.15,
      39.87,
      38.96,
      38.84,
      38.6,
      38.54,
      39.05,
      38.91,
      38.74,
      38.63,
      39.37,
      39.43,
      39.16,
      38.96,
      38.48,
      38.82,
      39.06,
      38.88,
      39.34,
      39.4,
      38.51,
      38.47,
      38.77,
      38.5,
      38.25,
      38.52,
      39.75,
      39.2,
      38.46,
      38.51,
      38.52,
      39.02,
      38.54,
      39.12,
      38.68,
      38.98,
      39.53,
      39.6,
      39.36,
      39.05,
      38.79,
      38.4,
      38.52,
      38.88,
      38.32,
      38.47,
      38.64,
      38.98,
      39.31,
      39.3,
      38.56,
      38.51,
      38.34,
      38.36,
      38.93,
      38.43,
      38.24,
      38.57,
      38.91,
      38.39,
      37.98,
      38.49,
      38.2,
      38.4,
      38.97,
      39.22,
      39.21,
      38.25,
      37.78,
      38.45,
      38.95,
      39.41,
      38.98,
      39.46,
      38.62,
      38.46,
      37.93,
      38.57,
      38.1,
      38.34,
      38.78,
      37.97,
      39.58,
      38.72,
      39.03,
      39.12,
      38.82,
      38.53,
      39.46,
      38.92,
      39.34,
      38.54,
      39.09,
      38.78,
      38.16,
      39.05,
      38.88,
      39.19,
      39.18,
      38.62,
      38.81,
      39.87,
      39.89,
      39.68,
      39.15,
      39.2,
      39.1,
      38.68,
      38.75,
      38.54,
      38.65,
      39.47,
      38.15,
      37.97,
      37.78,
      38.49,
      39.85,
      39.02,
      39.06,
      38.29,
      38.88,
      39.11,
      39.56,
      38.55,
      38.34,
      38.57,
      37.95,
      38.39,
      38.87,
      38.35,
      38.54,
      38.44,
      38.71,
      38.43,
      37.93,
      38.6,
      38.4,
      38.85,
      39.14,
      38.88,
      39.91,
      38.78,
      38.62,
      38.8,
      38.82,
      39.28,
      38.44,
      38.48,
      38.57,
      38.6,
      38.32,
      38.73,
      38.33,
      38.59,
      37.84,
      39.54,
      44.22,
      39.72,
      40.12,
      38.69,
      39.71,
      39.98,
      38.84,
      39.18,
      38.52,
      38.67,
      40.02,
      43.02,
      45.53,
      39.27,
      39.12,
      38.5,
      38.22,
      38.7,
      38.66,
      38.62,
      38.5,
      38.91,
      39.92,
      38.29,
      39.48,
      39.19,
      39.44,
      38.8,
      39.09,
      40.53,
      38.55,
      38.75,
      40.29,
      39.59,
      38.55,
      38.87,
      40.37,
      39.26,
      39.34,
      39.3,
      39.5,
      38.82,
      39.7,
      39.17,
      38.96,
      42.63,
      38.41,
      39.94,
      38.44,
      38.86,
      38.5,
      38.65,
      38.43,
      38.03,
      38.7,
      38.18,
      37.66,
      38.91,
      38.68,
      39.87,
      38.66,
      39.91,
      38.61,
      38.18,
      38.15,
      37.84,
      39.31,
      37.53,
      37.55,
      37.92,
      38.7,
      39.44,
      38.51,
      38.27,
      40.54,
      38.66,
      38.77,
      37.84,
      37.77,
      37.66,
      37.61,
      37.91,
      37.84,
      37.76,
      38.43,
      38.01,
      39.83,
      38.17,
      37.87,
      38.93,
      38.85,
      38.44,
      37.85,
      37.81,
      38.39,
      37.96,
      38.05,
      37.67,
      37.81,
      38.07,
      37.91,
      38.77,
      38.62,
      38.75,
      37.66,
      37.82,
      37.82,
      38.66,
      38.89,
      38.31,
      38.18,
      38.05,
      39.05,
      38.72,
      38.62,
      39.32,
      38.09,
      37.83,
      38.34,
      39.69,
      39.31,
      38.04,
      38.76,
      38.9,
      38.5,
      38.59,
      39.4,
      39.84,
      39.24,
      39.97,
      39.79,
      38.47,
      38.46,
      38.04,
      38.04,
      37.8,
      37.52,
      37.86,
      37.71,
      38.7,
      38.2,
      38.05,
      39.93,
      38.14,
      38.69,
      38.07,
      38.48,
      38.42,
      38.52,
      38.43,
      38.86,
      38.1,
      38.15,
      38.06,
      38.61,
      39.62,
      37.82,
      38.6,
      38.39,
      38.41,
      38.55,
      38.0,
      38.72,
      38.8,
      38.19,
      38.4,
      38.7,
      38.03,
      38.48,
      38.72,
      38.05,
      38.06,
      39.07,
      38.19,
      37.81,
      37.87,
      39.22,
      39.04,
      39.32,
      39.85,
      39.6,
      38.66,
      38.77,
      38.64,
      39.23,
      38.51,
      38.47,
      39.02,
      38.42,
      38.59,
      38.08,
      37.99,
      38.5,
      38.01,
      39.49,
      38.05,
      38.32,
      38.36,
      38.37,
      38.17,
      38.63,
      38.37,
      38.84,
      37.93,
      38.21,
      38.05,
      38.56,
      38.39,
      38.35,
      38.37,
      39.72,
      40.87,
      39.58,
      39.11,
      38.55,
      38.28,
      38.28,
      38.73,
      38.38,
      38.02,
      37.96,
      38.07,
      37.86,
      37.89,
      39.06,
      38.69,
      39.12,
      39.45,
      38.81,
      38.45,
      38.83,
      38.57,
      38.18,
      38.05,
      38.28,
      38.06,
      37.98,
      37.95,
      37.99,
      47.47,
      43.34,
      40.19,
      39.56,
      38.4,
      45.5,
      45.52,
      45.61,
      39.37,
      38.75,
      38.53,
      38.61,
      38.76,
      38.64,
      39.23,
      38.57,
      37.82,
      38.54,
      38.5,
      38.43,
      37.94,
      39.27,
      38.39,
      38.56,
      37.84,
      38.15,
      38.36,
      38.06,
      37.36,
      38.66,
      38.67,
      40.28,
      38.34,
      38.38,
      38.7,
      39.03,
      38.74,
      38.91,
      38.37,
      39.54,
      39.1,
      38.69,
      38.47,
      38.35,
      38.42,
      38.05,
      38.48,
      39.26,
      38.93,
      39.04,
      38.65,
      38.49,
      38.22,
      38.9,
      39.3,
      39.65,
      39.27,
      39.29,
      39.01,
      39.25,
      40.17,
      38.58,
      37.96,
      38.15,
      38.18,
      38.61,
      40.07,
      39.83,
      39.13,
      39.26,
      40.16,
      42.47,
      39.44,
      40.19,
      39.28,
      40.63,
      41.92,
      40.06,
      38.81,
      38.34,
      37.98,
      39.64,
      39.62,
      39.31,
      39.53,
      39.64,
      39.64,
      38.85,
      38.23,
      39.01,
      38.65,
      40.87,
      39.96,
      39.32,
      38.48,
      38.36,
      37.81,
      37.92,
      37.72,
      38.17,
      38.15,
      37.43,
      38.42,
      38.51,
      38.15,
      38.71,
      39.26,
      37.86,
      38.75,
      38.12,
      38.23,
      37.92,
      38.84,
      38.57,
      38.17,
      38.41,
      38.58,
      38.7,
      38.9,
      38.77,
      39.0,
      39.29,
      39.43,
      39.1,
      40.3,
      39.04,
      38.66,
      39.37,
      38.72,
      39.24,
      39.38,
      38.61,
      39.17,
      38.94,
      38.99,
      38.39,
      39.08,
      38.33,
      38.07,
      39.28,
      38.62,
      38.54,
      38.3,
      38.89,
      39.88,
      39.37,
      39.32,
      39.13,
      39.38,
      38.98,
      38.66,
      38.52,
      37.76,
      38.35,
      38.58,
      38.82,
      37.82,
      38.34,
      37.72,
      37.39,
      38.17,
      38.09,
      37.93,
      37.92,
      38.9,
      38.56,
      38.71,
      38.24,
      37.88,
      40.58,
      38.63,
      38.5,
      37.78,
      38.16,
      39.09,
      38.57,
      37.87,
      37.55,
      37.48,
      38.16,
      39.52,
      38.13,
      38.13,
      38.93,
      39.86,
      38.99,
      38.85,
      38.15,
      38.0,
      39.11,
      38.65,
      39.01,
      37.85,
      38.2,
      39.17,
      39.02,
      39.19,
      38.6,
      38.06,
      38.34,
      37.73,
      40.13,
      38.4,
      38.22,
      37.91,
      37.88,
      37.98,
      38.13,
      38.47,
      38.81,
      38.08,
      38.04,
      37.99,
      38.53,
      38.0,
      39.02,
      38.97,
      38.59,
      39.0,
      39.89,
      38.59,
      38.31,
      38.53,
      38.75,
      38.0,
      37.88,
      37.47,
      37.61,
      37.68,
      37.8,
      37.51,
      37.65,
      37.91,
      38.12,
      38.16,
      38.68,
      38.14,
      38.18,
      37.69,
      37.89,
      39.01,
      40.41,
      39.96,
      39.18,
      38.84,
      39.58,
      38.67,
      37.9,
      37.75,
      38.11,
      38.13,
      40.1,
      38.53,
      37.88,
      40.21,
      38.69,
      38.34,
      37.89,
      39.07,
      38.45,
      38.19,
      38.25,
      38.59,
      39.25,
      38.29,
      39.16,
      38.69,
      37.99,
      37.73,
      38.22,
      38.38,
      38.27,
      37.89,
      38.48,
      38.0,
      37.86,
      38.3,
      38.36,
      37.93,
      39.24,
      39.47,
      38.46,
      38.42,
      40.08,
      38.09,
      38.1,
      38.43,
      38.3,
      38.28,
      38.22,
      37.8,
      38.08,
      38.77,
      38.97,
      39.56,
      39.06,
      38.82,
      38.48,
      38.45,
      38.82,
      41.44,
      39.55,
      38.04,
      37.79,
      37.86,
      38.37,
      37.9,
      38.19,
      37.61,
      38.21,
      38.45,
      40.94,
      42.82,
      41.04,
      40.18,
      41.76,
      40.86,
      45.76,
      46.06,
      44.05,
      44.66,
      46.11,
      44.84,
      44.16,
      44.64,
      38.29,
      40.62,
      42.55,
      38.97,
      38.32,
      38.67,
      38.5,
      38.21,
      37.87,
      37.88,
      37.97,
      39.45,
      38.93,
      38.35,
      38.58,
      38.33,
      38.27,
      37.65,
      38.01,
      37.85,
      38.06,
      38.09,
      38.71,
      37.8,
      41.58,
      39.11,
      37.9,
      38.33,
      38.86,
      39.13,
      38.24,
      37.7,
      37.56,
      38.21,
      37.7,
      40.01,
      39.85,
      39.43,
      39.03,
      38.36,
      41.38,
      39.76,
      38.05,
      38.03,
      38.04,
      37.81,
      37.85,
      38.22,
      38.47,
      38.26,
      37.37,
      37.7,
      37.78,
      38.77,
      38.67,
      39.42,
      39.79,
      39.82,
      39.57,
      38.73,
      38.18,
      37.88,
      38.14,
      38.91,
      38.15,
      37.8,
      37.66,
      37.66,
      37.65,
      37.53,
      37.55,
      37.66,
      38.11,
      38.88,
      38.8,
      37.82,
      37.84,
      37.83,
      37.71,
      37.86,
      38.11,
      39.12,
      37.69,
      37.99,
      38.58,
      39.01,
      37.93,
      37.83,
      38.3,
      38.15,
      38.47,
      38.04,
      38.62,
      38.23,
      37.69,
      39.56,
      39.47,
      38.18,
      38.81,
      38.22,
      38.0,
      37.84,
      37.75,
      37.69,
      37.94,
      38.81,
      38.67,
      38.24,
      37.94,
      37.57,
      38.62,
      38.21,
      38.1,
      38.01,
      38.07,
      37.71,
      37.69,
      37.84,
      37.7,
      37.61,
      38.48,
      38.6,
      38.78,
      37.83,
      37.54,
      38.06,
      38.2,
      38.08,
      38.63,
      37.85,
      37.95,
      37.83,
      37.7,
      38.81,
      38.82,
      38.6,
      37.87,
      38.4,
      37.69,
      37.82,
      38.81,
      39.12,
      38.29,
      38.06,
      38.68,
      39.03,
      39.44,
      38.77,
      37.82,
      37.62,
      38.58,
      38.23,
      38.0,
      38.16,
      38.83,
      39.68,
      38.68,
      38.04,
      39.43,
      38.12,
      37.81,
      38.02,
      37.99,
      37.88,
      38.26,
      39.7,
      39.55,
      38.56,
      39.32,
      38.59,
      38.97,
      38.3,
      38.42,
      38.16,
      39.0,
      37.98,
      38.16,
      38.77,
      38.26,
      38.69,
      39.04,
      38.3,
      38.9,
      38.58,
      39.12,
      38.87,
      38.68,
      38.53,
      38.45,
      38.61,
      38.18,
      37.88,
      38.47,
      38.31,
      38.14,
      37.86,
      37.62,
      37.74,
      37.57,
      40.38,
      39.41,
      38.56,
      39.0,
      38.88,
      45.39,
      38.74,
      39.01,
      38.1,
      38.51,
      38.26,
      38.82,
      38.3,
      38.91,
      38.98,
      39.06,
      39.51,
      38.81,
      38.02,
      38.7,
      38.74,
      38.33,
      37.92,
      38.25,
      38.93,
      38.17,
      38.69,
      38.53,
      38.66,
      38.0,
      37.95,
      38.04,
      38.54,
      39.26,
      39.28,
      38.83,
      39.01,
      38.94,
      39.79,
      39.62,
      38.7,
      39.42,
      39.29,
      39.33,
      39.81,
      39.97,
      39.7,
      38.43,
      37.89,
      37.68,
      38.03,
      38.47,
      38.13,
      38.32,
      38.75,
      38.66,
      38.71,
      38.39,
      38.1,
      38.79,
      38.26,
      38.08,
      38.17,
      38.17,
      38.77,
      38.56,
      38.77,
      39.17,
      38.13,
      37.89,
      38.6,
      37.84,
      39.21,
      38.94,
      38.46,
      39.01,
      39.46,
      38.43,
      38.04,
      38.7,
      38.83,
      38.65,
      38.62,
      38.78,
      38.02,
      37.66,
      38.27,
      38.09,
      37.94,
      37.73,
      37.73,
      38.53,
      38.13,
      38.73,
      38.76,
      38.29,
      38.08,
      37.56,
      37.54,
      37.62,
      37.69,
      38.09,
      38.18,
      38.69,
      38.38,
      39.34,
      38.78,
      39.79,
      38.75,
      39.21,
      38.57,
      38.62,
      38.25,
      39.22,
      38.11,
      37.58,
      37.69,
      37.98,
      37.85,
      38.72,
      37.75,
      37.56,
      37.59,
      38.91,
      38.49,
      38.05,
      38.79,
      38.45,
      38.56,
      38.89,
      38.85,
      39.15,
      37.79,
      37.66,
      38.52,
      39.52,
      39.75,
      38.08,
      38.59,
      38.87,
      39.87,
      38.56,
      38.57,
      38.27,
      37.81,
      37.75,
      38.15,
      38.01,
      37.93,
      52.04,
      38.03,
      38.19,
      40.17,
      39.23,
      38.53,
      37.59,
      37.84,
      37.79,
      37.91,
      38.01,
      38.46,
      37.99,
      38.01,
      38.4,
      38.57,
      37.84,
      38.38,
      37.95,
      38.78,
      39.11,
      38.25,
      38.14,
      38.17,
      38.66,
      38.24,
      38.4,
      39.51,
      39.88,
      39.26,
      38.84,
      38.45,
      38.55,
      37.96,
      38.15,
      38.97,
      38.27,
      37.99,
      38.13,
      37.75,
      37.6,
      38.23,
      37.92,
      38.61,
      38.51,
      38.22,
      38.28,
      49.2,
      39.7,
      39.68,
      39.32,
      39.61,
      38.82,
      38.76,
      38.53,
      38.42,
      38.06,
      38.52,
      38.93,
      38.56,
      38.36,
      37.93,
      38.04,
      40.66,
      38.3,
      38.44,
      38.84,
      37.93,
      38.09,
      38.46,
      38.26,
      38.07,
      37.96,
      37.84,
      38.84,
      38.18,
      38.18,
      38.46,
      38.69,
      38.17,
      37.78,
      37.72,
      37.85,
      38.46,
      38.71,
      38.24,
      38.43,
      38.09,
      38.29,
      38.14,
      39.39,
      38.26,
      38.63,
      38.99,
      39.34,
      38.67,
      38.07,
      38.24,
      38.27,
      37.6,
      37.84,
      38.84,
      38.34,
      37.94,
      37.81,
      37.95,
      37.9,
      38.91,
      39.68,
      38.46,
      38.51,
      37.49,
      37.74,
      38.06,
      38.62,
      38.73,
      38.35,
      38.95,
      38.27,
      38.36,
      38.44,
      37.84,
      38.53,
      38.72,
      38.74,
      38.77,
      38.03,
      37.99,
      37.79,
      38.85,
      38.64,
      38.83,
      37.87,
      38.88,
      38.8,
      38.69,
      38.64,
      38.34,
      38.8,
      38.67,
      37.91,
      37.95,
      38.22,
      38.48,
      38.08,
      38.08,
      37.79,
      37.98,
      37.72,
      38.55,
      38.12,
      38.25,
      38.43,
      38.37,
      39.23,
      38.54,
      38.88,
      38.17,
      38.03,
      38.18,
      38.82,
      37.78,
      37.72,
      38.0,
      37.85,
      37.87,
      37.67,
      39.54,
      38.27,
      37.81,
      38.7,
      38.51,
      39.03,
      38.63,
      39.85,
      39.04,
      39.35,
      40.69,
      39.15,
      39.78,
      39.12,
      38.36,
      37.97,
      38.54,
      38.7,
      38.55,
      38.29,
      38.3,
      37.89,
      38.27,
      38.37,
      38.18,
      38.7,
      39.28,
      37.79,
      37.78,
      37.85,
      37.55,
      37.74,
      37.73,
      37.83,
      38.35,
      39.33,
      38.42,
      38.64,
      38.9,
      38.64,
      39.31,
      38.73,
      37.86,
      38.35,
      38.91,
      38.89,
      38.29,
      39.21,
      37.92,
      38.2,
      38.33,
      37.95,
      37.69,
      38.46,
      39.0,
      38.21,
      38.39,
      39.83,
      38.86,
      39.08,
      39.65,
      38.83,
      39.15,
      39.73,
      39.2,
      38.76,
      38.17,
      37.94,
      38.81,
      38.72,
      38.48,
      38.24,
      39.06,
      38.82,
      38.85,
      40.18,
      39.27,
      38.53,
      38.15,
      38.21,
      37.86,
      38.0,
      38.8,
      39.19,
      38.67,
      38.5,
      38.97,
      38.13,
      38.24,
      38.28,
      39.58,
      38.83,
      38.81,
      37.92,
      38.56,
      39.46,
      38.09,
      38.03,
      38.78,
      38.15,
      37.77,
      38.16,
      39.24,
      38.94,
      37.78,
      38.33,
      38.85,
      38.3,
      38.59,
      38.74,
      38.48,
      37.55,
      37.99,
      37.74,
      39.4,
      38.27,
      39.03,
      39.03,
      38.66,
      37.8,
      40.67,
      39.51,
      39.0,
      38.63,
      38.8,
      37.83,
      37.54,
      37.68,
      38.16,
      38.4,
      38.55,
      39.56,
      39.27,
      39.86,
      38.9,
      38.49,
      38.31,
      38.33,
      38.08,
      38.44,
      38.52,
      38.7,
      39.18,
      38.96,
      37.89,
      38.17,
      37.67,
      38.22,
      37.98,
      38.32,
      41.3,
      39.24,
      38.81,
      39.11,
      39.2,
      38.79,
      38.8,
      38.87,
      40.05,
      39.25,
      39.16,
      38.41,
      38.66,
      38.94,
      38.94,
      39.33,
      38.74,
      38.25,
      38.83,
      39.34,
      39.14,
      38.87,
      38.17,
      38.12,
      38.67,
      38.81,
      38.52,
      38.67,
      38.5,
      39.09,
      39.21,
      38.83,
      38.48,
      38.91,
      39.2,
      39.09,
      39.7,
      39.35,
      38.7,
      38.73,
      38.14,
      38.27,
      38.21,
      37.84,
      38.24,
      39.36,
      39.35,
      38.93,
      38.02,
      37.9,
      39.31,
      39.44,
      38.98,
      38.9,
      39.25,
      39.17,
      38.86,
      38.93,
      39.44,
      39.41,
      40.84,
      39.17,
      37.94,
      38.78,
      40.29,
      39.44,
      39.45,
      40.01,
      39.14,
      38.55,
      39.03,
      39.35,
      39.36,
      39.55,
      38.54,
      39.24,
      38.92,
      39.59,
      39.13,
      38.45,
      38.45,
      38.57,
      38.39,
      37.92,
      38.28,
      38.63,
      38.82,
      40.74,
      38.44,
      37.99,
      40.02,
      39.32,
      39.71,
      39.74,
      39.52,
      39.19,
      38.94,
      39.65,
      38.7,
      38.61,
      38.91,
      39.8,
      39.8,
      39.06,
      38.61,
      38.01,
      37.96,
      37.58,
      37.94,
      39.21,
      38.86,
      38.28,
      38.68,
      37.82,
      38.03,
      37.89,
      39.27,
      38.24,
      38.56,
      38.28,
      39.14,
      39.64,
      39.9,
      39.42,
      39.32,
      39.61,
      38.94,
      39.3,
      39.19,
      39.12,
      39.67,
      39.19,
      39.42,
      39.51,
      39.0,
      39.36,
      39.46,
      39.51,
      39.27,
      39.14,
      39.38,
      39.16,
      39.17,
      39.46,
      39.2,
      39.51,
      39.38,
      39.24,
      39.33,
      39.21,
      39.38,
      40.14,
      40.73,
      39.85,
      39.35,
      39.76,
      39.38,
      39.04,
      38.97,
      38.85,
      39.14,
      39.34,
      39.08,
      38.82,
      38.83,
      38.6,
      38.67,
      38.5,
      38.4,
      38.58,
      38.46,
      38.27,
      41.76,
      38.62,
      38.57,
      39.26,
      38.73,
      39.1,
      39.03,
      38.38,
      38.24,
      38.41,
      39.08,
      40.09,
      38.92,
      39.19,
      38.91,
      38.54,
      39.35,
      39.2,
      38.85,
      38.94,
      38.64,
      47.23,
      38.75,
      38.55,
      38.53,
      38.53,
      38.88,
      38.63,
      38.47,
      38.39,
      38.78,
      39.61,
      39.19,
      42.07,
      38.72,
      38.73,
      38.24,
      38.17,
      39.86,
      38.81,
      38.57,
      39.56,
      39.59,
      39.16,
      38.24,
      38.81,
      39.34,
      39.2,
      39.68,
      39.85,
      39.56,
      39.49,
      38.95,
      39.28,
      39.06,
      39.3,
      39.33,
      39.38,
      38.28,
      39.19,
      39.07,
      39.31,
      39.38,
      39.18,
      40.06,
      39.39,
      38.7,
      39.71,
      39.81,
      40.06,
      39.67,
      39.68,
      39.32,
      39.44,
      39.83,
      39.38,
      39.97,
      39.58,
      39.14,
      39.6,
      39.16,
      39.39,
      39.68,
      39.39,
      38.74,
      38.61,
      39.58,
      39.46,
      39.73,
      38.99,
      38.86,
      38.41,
      37.93,
      38.33,
      38.76,
      38.64,
      38.24,
      38.27,
      38.82,
      38.58,
      39.12,
      42.04,
      38.25,
      37.87,
      37.89,
      38.24,
      37.76,
      38.27,
      39.06,
      37.81,
      37.62,
      37.66,
      38.12,
      38.82,
      38.19,
      37.91,
      37.59,
      37.46,
      37.63,
      38.67,
      38.67,
      38.08,
      37.76,
      38.0,
      37.77,
      37.66,
      37.63,
      37.6,
      38.28,
      37.77,
      37.64,
      38.75,
      37.65,
      38.19,
      39.74,
      38.36,
      38.07,
      37.74,
      37.5,
      38.23,
      38.12,
      38.27,
      38.77,
      37.9,
      39.86,
      37.76,
      37.9,
      37.5,
      37.55,
      37.44,
      37.49,
      37.67,
      37.54,
      38.38,
      38.33,
      39.1,
      37.68,
      37.61,
      39.38,
      39.47,
      39.69,
      39.22,
      38.99,
      38.93,
      38.07,
      38.43,
      38.14,
      37.83,
      38.42,
      38.65,
      38.47,
      38.48,
      37.76,
      37.83,
      37.79,
      37.33,
      37.98,
      38.45,
      38.49,
      38.92,
      39.95,
      38.87,
      39.13,
      38.92,
      38.87,
      38.95,
      38.67,
      38.08,
      38.93,
      38.62,
      39.8,
      39.15,
      37.89,
      38.02,
      39.94,
      39.31,
      39.38,
      39.18,
      38.17,
      38.3,
      38.82,
      38.69,
      37.88,
      38.18,
      37.66,
      38.07,
      38.29,
      39.18,
      39.07,
      39.25,
      38.34,
      38.46,
      38.35,
      38.04,
      38.9,
      38.75,
      38.53,
      39.1,
      40.19,
      39.68,
      39.94,
      38.98,
      38.8,
      39.42,
      38.94,
      38.55,
      38.17,
      38.34,
      38.48,
      38.68,
      38.28,
      38.06,
      38.76,
      38.5,
      38.78,
      38.34,
      37.94,
      37.98,
      38.58,
      38.09,
      38.36,
      38.1,
      38.18,
      38.75,
      38.71,
      37.89,
      38.49,
      38.66,
      38.45,
      38.25,
      38.11,
      38.4,
      37.95,
      39.35,
      39.43,
      38.31,
      38.13,
      37.84,
      38.45,
      39.25,
      38.57,
      38.55,
      37.94,
      37.87,
      38.02,
      37.83,
      38.39,
      37.73,
      38.31,
      38.33,
      38.02,
      37.65,
      37.49,
      37.72,
      38.32,
      38.84,
      38.74,
      38.3,
      39.18,
      38.47,
      38.92,
      38.81,
      38.13,
      38.31,
      38.2,
      39.32,
      39.28,
      39.06,
      38.46,
      38.55,
      37.64,
      37.86,
      38.45,
      38.12,
      38.54,
      37.88,
      37.54,
      37.99,
      38.21,
      38.26,
      37.89,
      37.88,
      37.46,
      37.84,
      38.71,
      38.45,
      38.56,
      38.78,
      38.46,
      37.74,
      37.64,
      38.17,
      38.3,
      37.7,
      38.2,
      38.27,
      38.0,
      38.12,
      37.75,
      39.54,
      39.15,
      38.68,
      38.87,
      38.99,
      38.57,
      38.35,
      39.08,
      39.28,
      38.06,
      38.87,
      38.94,
      39.03,
      38.89,
      38.89,
      38.92,
      39.99,
      38.92,
      38.84,
      39.08,
      38.58,
      39.1,
      38.23,
      37.37,
      37.63,
      38.83,
      39.21,
      40.12,
      39.54,
      40.2,
      39.22,
      38.86,
      39.47,
      40.69,
      38.51,
      39.05,
      38.29,
      37.81,
      38.04,
      38.15,
      38.31,
      38.89,
      38.11,
      38.06,
      37.68,
      38.44,
      40.16,
      38.6,
      37.73,
      38.35,
      38.4,
      40.08,
      38.84,
      38.6,
      38.29,
      38.71,
      39.4,
      38.48,
      38.37,
      38.45,
      38.06,
      38.85,
      37.91,
      37.64,
      37.85,
      38.14,
      38.74,
      38.45,
      38.38,
      38.24,
      38.17,
      38.29,
      38.17,
      37.7,
      38.01,
      37.69,
      38.19,
      37.9,
      37.81,
      39.17,
      38.04,
      38.86,
      39.1,
      38.13,
      37.61,
      37.61,
      38.02,
      37.72,
      37.93,
      38.49,
      38.1,
      38.41,
      37.31,
      37.97,
      38.28,
      38.67,
      38.41,
      38.2,
      37.93,
      38.58,
      38.87,
      38.76,
      39.05,
      38.38,
      38.64,
      38.09,
      37.61,
      37.94,
      38.85,
      38.24,
      38.44,
      38.62,
      38.08,
      38.68,
      38.68,
      38.24,
      38.09,
      37.94,
      38.12,
      38.15,
      37.94,
      38.65,
      38.17,
      38.49,
      38.22,
      38.04,
      38.97,
      38.5,
      38.67,
      39.34,
      38.48,
      38.65,
      38.55,
      37.83,
      37.81,
      38.33,
      37.91,
      38.49,
      38.0
    ],
    "avg_latency_ms": 38.81,
    "p50_latency_ms": 38.67,
    "p95_latency_ms": 40.02,
    "p99_latency_ms": 42.81
  },
  "episode_details": [
    {
      "task_id": 0,
      "episode_idx": 0,
      "task_name": "open_the_middle_drawer_of_the_cabinet_table_1.bddl",
      "task_description": "open the middle drawer of the cabinet table 1",
      "perturb_info": {
        "base_suite": "open"
      },
      "success": false,
      "steps": 310,
      "avg_latency_ms": 38.58
    },
    {
      "task_id": 0,
      "episode_idx": 1,
      "task_name": "open_the_middle_drawer_of_the_cabinet_table_1.bddl",
      "task_description": "open the middle drawer of the cabinet table 1",
      "perturb_info": {
        "base_suite": "open"
      },
      "success": false,
      "steps": 310,
      "avg_latency_ms": 38.84
    },
    {
      "task_id": 0,
      "episode_idx": 2,
      "task_name": "open_the_middle_drawer_of_the_cabinet_table_1.bddl",
      "task_description": "open the middle drawer of the cabinet table 1",
      "perturb_info": {
        "base_suite": "open"
      },
      "success": false,
      "steps": 310,
      "avg_latency_ms": 39.13
    },
    {
      "task_id": 0,
      "episode_idx": 3,
      "task_name": "open_the_middle_drawer_of_the_cabinet_table_1.bddl",
      "task_description": "open the middle drawer of the cabinet table 1",
      "perturb_info": {
        "base_suite": "open"
      },
      "success": false,
      "steps": 310,
      "avg_latency_ms": 39.35
    },
    {
      "task_id": 0,
      "episode_idx": 4,
      "task_name": "open_the_middle_drawer_of_the_cabinet_table_1.bddl",
      "task_description": "open the middle drawer of the cabinet table 1",
      "perturb_info": {
        "base_suite": "open"
      },
      "success": false,
      "steps": 310,
      "avg_latency_ms": 39.11
    },
    {
      "task_id": 1,
      "episode_idx": 0,
      "task_name": "open_the_middle_drawer_of_the_cabinet_table_10.bddl",
      "task_description": "open the middle drawer of the cabinet table 10",
      "perturb_info": {
        "base_suite": "open"
      },
      "success": false,
      "steps": 310,
      "avg_latency_ms": 39.38
    },
    {
      "task_id": 1,
      "episode_idx": 1,
      "task_name": "open_the_middle_drawer_of_the_cabinet_table_10.bddl",
      "task_description": "open the middle drawer of the cabinet table 10",
      "perturb_info": {
        "base_suite": "open"
      },
      "success": false,
      "steps": 310,
      "avg_latency_ms": 38.84
    },
    {
      "task_id": 1,
      "episode_idx": 2,
      "task_name": "open_the_middle_drawer_of_the_cabinet_table_10.bddl",
      "task_description": "open the middle drawer of the cabinet table 10",
      "perturb_info": {
        "base_suite": "open"
      },
      "success": false,
      "steps": 310,
      "avg_latency_ms": 38.79
    },
    {
      "task_id": 1,
      "episode_idx": 3,
      "task_name": "open_the_middle_drawer_of_the_cabinet_table_10.bddl",
      "task_description": "open the middle drawer of the cabinet table 10",
      "perturb_info": {
        "base_suite": "open"
      },
      "success": false,
      "steps": 310,
      "avg_latency_ms": 38.7
    },
    {
      "task_id": 1,
      "episode_idx": 4,
      "task_name": "open_the_middle_drawer_of_the_cabinet_table_10.bddl",
      "task_description": "open the middle drawer of the cabinet table 10",
      "perturb_info": {
        "base_suite": "open"
      },
      "success": false,
      "steps": 310,
      "avg_latency_ms": 38.46
    },
    {
      "task_id": 2,
      "episode_idx": 0,
      "task_name": "open_the_middle_drawer_of_the_cabinet_table_12.bddl",
      "task_description": "open the middle drawer of the cabinet table 12",
      "perturb_info": {
        "base_suite": "open"
      },
      "success": false,
      "steps": 310,
      "avg_latency_ms": 38.48
    },
    {
      "task_id": 2,
      "episode_idx": 1,
      "task_name": "open_the_middle_drawer_of_the_cabinet_table_12.bddl",
      "task_description": "open the middle drawer of the cabinet table 12",
      "perturb_info": {
        "base_suite": "open"
      },
      "success": false,
      "steps": 310,
      "avg_latency_ms": 39.46
    },
    {
      "task_id": 2,
      "episode_idx": 2,
      "task_name": "open_the_middle_drawer_of_the_cabinet_table_12.bddl",
      "task_description": "open the middle drawer of the cabinet table 12",
      "perturb_info": {
        "base_suite": "open"
      },
      "success": false,
      "steps": 310,
      "avg_latency_ms": 39.27
    },
    {
      "task_id": 2,
      "episode_idx": 3,
      "task_name": "open_the_middle_drawer_of_the_cabinet_table_12.bddl",
      "task_description": "open the middle drawer of the cabinet table 12",
      "perturb_info": {
        "base_suite": "open"
      },
      "success": false,
      "steps": 310,
      "avg_latency_ms": 39.26
    },
    {
      "task_id": 2,
      "episode_idx": 4,
      "task_name": "open_the_middle_drawer_of_the_cabinet_table_12.bddl",
      "task_description": "open the middle drawer of the cabinet table 12",
      "perturb_info": {
        "base_suite": "open"
      },
      "success": false,
      "steps": 310,
      "avg_latency_ms": 39.23
    },
    {
      "task_id": 3,
      "episode_idx": 0,
      "task_name": "open_the_middle_drawer_of_the_cabinet_table_13.bddl",
      "task_description": "open the middle drawer of the cabinet table 13",
      "perturb_info": {
        "base_suite": "open"
      },
      "success": false,
      "steps": 310,
      "avg_latency_ms": 39.75
    },
    {
      "task_id": 3,
      "episode_idx": 1,
      "task_name": "open_the_middle_drawer_of_the_cabinet_table_13.bddl",
      "task_description": "open the middle drawer of the cabinet table 13",
      "perturb_info": {
        "base_suite": "open"
      },
      "success": false,
      "steps": 310,
      "avg_latency_ms": 38.75
    },
    {
      "task_id": 3,
      "episode_idx": 2,
      "task_name": "open_the_middle_drawer_of_the_cabinet_table_13.bddl",
      "task_description": "open the middle drawer of the cabinet table 13",
      "perturb_info": {
        "base_suite": "open"
      },
      "success": false,
      "steps": 310,
      "avg_latency_ms": 38.73
    },
    {
      "task_id": 3,
      "episode_idx": 3,
      "task_name": "open_the_middle_drawer_of_the_cabinet_table_13.bddl",
      "task_description": "open the middle drawer of the cabinet table 13",
      "perturb_info": {
        "base_suite": "open"
      },
      "success": false,
      "steps": 310,
      "avg_latency_ms": 38.77
    },
    {
      "task_id": 3,
      "episode_idx": 4,
      "task_name": "open_the_middle_drawer_of_the_cabinet_table_13.bddl",
      "task_description": "open the middle drawer of the cabinet table 13",
      "perturb_info": {
        "base_suite": "open"
      },
      "success": false,
      "steps": 310,
      "avg_latency_ms": 39.37
    },
    {
      "task_id": 4,
      "episode_idx": 0,
      "task_name": "open_the_middle_drawer_of_the_cabinet_table_15.bddl",
      "task_description": "open the middle drawer of the cabinet table 15",
      "perturb_info": {
        "base_suite": "open"
      },
      "success": false,
      "steps": 310,
      "avg_latency_ms": 38.37
    },
    {
      "task_id": 4,
      "episode_idx": 1,
      "task_name": "open_the_middle_drawer_of_the_cabinet_table_15.bddl",
      "task_description": "open the middle drawer of the cabinet table 15",
      "perturb_info": {
        "base_suite": "open"
      },
      "success": false,
      "steps": 310,
      "avg_latency_ms": 38.56
    },
    {
      "task_id": 4,
      "episode_idx": 2,
      "task_name": "open_the_middle_drawer_of_the_cabinet_table_15.bddl",
      "task_description": "open the middle drawer of the cabinet table 15",
      "perturb_info": {
        "base_suite": "open"
      },
      "success": false,
      "steps": 310,
      "avg_latency_ms": 38.56
    },
    {
      "task_id": 4,
      "episode_idx": 3,
      "task_name": "open_the_middle_drawer_of_the_cabinet_table_15.bddl",
      "task_description": "open the middle drawer of the cabinet table 15",
      "perturb_info": {
        "base_suite": "open"
      },
      "success": false,
      "steps": 310,
      "avg_latency_ms": 39.3
    },
    {
      "task_id": 4,
      "episode_idx": 4,
      "task_name": "open_the_middle_drawer_of_the_cabinet_table_15.bddl",
      "task_description": "open the middle drawer of the cabinet table 15",
      "perturb_info": {
        "base_suite": "open"
      },
      "success": false,
      "steps": 310,
      "avg_latency_ms": 38.97
    },
    {
      "task_id": 5,
      "episode_idx": 0,
      "task_name": "open_the_middle_drawer_of_the_cabinet_table_16.bddl",
      "task_description": "open the middle drawer of the cabinet table 16",
      "perturb_info": {
        "base_suite": "open"
      },
      "success": false,
      "steps": 310,
      "avg_latency_ms": 38.66
    },
    {
      "task_id": 5,
      "episode_idx": 1,
      "task_name": "open_the_middle_drawer_of_the_cabinet_table_16.bddl",
      "task_description": "open the middle drawer of the cabinet table 16",
      "perturb_info": {
        "base_suite": "open"
      },
      "success": false,
      "steps": 310,
      "avg_latency_ms": 38.4
    },
    {
      "task_id": 5,
      "episode_idx": 2,
      "task_name": "open_the_middle_drawer_of_the_cabinet_table_16.bddl",
      "task_description": "open the middle drawer of the cabinet table 16",
      "perturb_info": {
        "base_suite": "open"
      },
      "success": false,
      "steps": 310,
      "avg_latency_ms": 38.61
    },
    {
      "task_id": 5,
      "episode_idx": 3,
      "task_name": "open_the_middle_drawer_of_the_cabinet_table_16.bddl",
      "task_description": "open the middle drawer of the cabinet table 16",
      "perturb_info": {
        "base_suite": "open"
      },
      "success": false,
      "steps": 310,
      "avg_latency_ms": 39.69
    },
    {
      "task_id": 5,
      "episode_idx": 4,
      "task_name": "open_the_middle_drawer_of_the_cabinet_table_16.bddl",
      "task_description": "open the middle drawer of the cabinet table 16",
      "perturb_info": {
        "base_suite": "open"
      },
      "success": false,
      "steps": 310,
      "avg_latency_ms": 38.39
    },
    {
      "task_id": 6,
      "episode_idx": 0,
      "task_name": "open_the_middle_drawer_of_the_cabinet_table_17.bddl",
      "task_description": "open the middle drawer of the cabinet table 17",
      "perturb_info": {
        "base_suite": "open"
      },
      "success": false,
      "steps": 310,
      "avg_latency_ms": 38.25
    },
    {
      "task_id": 6,
      "episode_idx": 1,
      "task_name": "open_the_middle_drawer_of_the_cabinet_table_17.bddl",
      "task_description": "open the middle drawer of the cabinet table 17",
      "perturb_info": {
        "base_suite": "open"
      },
      "success": false,
      "steps": 310,
      "avg_latency_ms": 38.69
    },
    {
      "task_id": 6,
      "episode_idx": 2,
      "task_name": "open_the_middle_drawer_of_the_cabinet_table_17.bddl",
      "task_description": "open the middle drawer of the cabinet table 17",
      "perturb_info": {
        "base_suite": "open"
      },
      "success": false,
      "steps": 310,
      "avg_latency_ms": 38.65
    },
    {
      "task_id": 6,
      "episode_idx": 3,
      "task_name": "open_the_middle_drawer_of_the_cabinet_table_17.bddl",
      "task_description": "open the middle drawer of the cabinet table 17",
      "perturb_info": {
        "base_suite": "open"
      },
      "success": false,
      "steps": 310,
      "avg_latency_ms": 38.37
    },
    {
      "task_id": 6,
      "episode_idx": 4,
      "task_name": "open_the_middle_drawer_of_the_cabinet_table_17.bddl",
      "task_description": "open the middle drawer of the cabinet table 17",
      "perturb_info": {
        "base_suite": "open"
      },
      "success": false,
      "steps": 310,
      "avg_latency_ms": 38.63
    },
    {
      "task_id": 7,
      "episode_idx": 0,
      "task_name": "open_the_middle_drawer_of_the_cabinet_table_18.bddl",
      "task_description": "open the middle drawer of the cabinet table 18",
      "perturb_info": {
        "base_suite": "open"
      },
      "success": false,
      "steps": 310,
      "avg_latency_ms": 38.63
    },
    {
      "task_id": 7,
      "episode_idx": 1,
      "task_name": "open_the_middle_drawer_of_the_cabinet_table_18.bddl",
      "task_description": "open the middle drawer of the cabinet table 18",
      "perturb_info": {
        "base_suite": "open"
      },
      "success": false,
      "steps": 310,
      "avg_latency_ms": 38.34
    },
    {
      "task_id": 7,
      "episode_idx": 2,
      "task_name": "open_the_middle_drawer_of_the_cabinet_table_18.bddl",
      "task_description": "open the middle drawer of the cabinet table 18",
      "perturb_info": {
        "base_suite": "open"
      },
      "success": false,
      "steps": 310,
      "avg_latency_ms": 38.58
    },
    {
      "task_id": 7,
      "episode_idx": 3,
      "task_name": "open_the_middle_drawer_of_the_cabinet_table_18.bddl",
      "task_description": "open the middle drawer of the cabinet table 18",
      "perturb_info": {
        "base_suite": "open"
      },
      "success": false,
      "steps": 310,
      "avg_latency_ms": 38.6
    },
    {
      "task_id": 7,
      "episode_idx": 4,
      "task_name": "open_the_middle_drawer_of_the_cabinet_table_18.bddl",
      "task_description": "open the middle drawer of the cabinet table 18",
      "perturb_info": {
        "base_suite": "open"
      },
      "success": false,
      "steps": 310,
      "avg_latency_ms": 38.77
    },
    {
      "task_id": 8,
      "episode_idx": 0,
      "task_name": "open_the_middle_drawer_of_the_cabinet_table_19.bddl",
      "task_description": "open the middle drawer of the cabinet table 19",
      "perturb_info": {
        "base_suite": "open"
      },
      "success": false,
      "steps": 310,
      "avg_latency_ms": 38.95
    },
    {
      "task_id": 8,
      "episode_idx": 1,
      "task_name": "open_the_middle_drawer_of_the_cabinet_table_19.bddl",
      "task_description": "open the middle drawer of the cabinet table 19",
      "perturb_info": {
        "base_suite": "open"
      },
      "success": false,
      "steps": 310,
      "avg_latency_ms": 39.07
    },
    {
      "task_id": 8,
      "episode_idx": 2,
      "task_name": "open_the_middle_drawer_of_the_cabinet_table_19.bddl",
      "task_description": "open the middle drawer of the cabinet table 19",
      "perturb_info": {
        "base_suite": "open"
      },
      "success": false,
      "steps": 310,
      "avg_latency_ms": 39.16
    },
    {
      "task_id": 8,
      "episode_idx": 3,
      "task_name": "open_the_middle_drawer_of_the_cabinet_table_19.bddl",
      "task_description": "open the middle drawer of the cabinet table 19",
      "perturb_info": {
        "base_suite": "open"
      },
      "success": false,
      "steps": 310,
      "avg_latency_ms": 39.22
    },
    {
      "task_id": 8,
      "episode_idx": 4,
      "task_name": "open_the_middle_drawer_of_the_cabinet_table_19.bddl",
      "task_description": "open the middle drawer of the cabinet table 19",
      "perturb_info": {
        "base_suite": "open"
      },
      "success": false,
      "steps": 310,
      "avg_latency_ms": 38.16
    },
    {
      "task_id": 9,
      "episode_idx": 0,
      "task_name": "open_the_middle_drawer_of_the_cabinet_table_2.bddl",
      "task_description": "open the middle drawer of the cabinet table 2",
      "perturb_info": {
        "base_suite": "open"
      },
      "success": false,
      "steps": 310,
      "avg_latency_ms": 38.64
    },
    {
      "task_id": 9,
      "episode_idx": 1,
      "task_name": "open_the_middle_drawer_of_the_cabinet_table_2.bddl",
      "task_description": "open the middle drawer of the cabinet table 2",
      "perturb_info": {
        "base_suite": "open"
      },
      "success": false,
      "steps": 310,
      "avg_latency_ms": 38.45
    },
    {
      "task_id": 9,
      "episode_idx": 2,
      "task_name": "open_the_middle_drawer_of_the_cabinet_table_2.bddl",
      "task_description": "open the middle drawer of the cabinet table 2",
      "perturb_info": {
        "base_suite": "open"
      },
      "success": false,
      "steps": 310,
      "avg_latency_ms": 38.48
    },
    {
      "task_id": 9,
      "episode_idx": 3,
      "task_name": "open_the_middle_drawer_of_the_cabinet_table_2.bddl",
      "task_description": "open the middle drawer of the cabinet table 2",
      "perturb_info": {
        "base_suite": "open"
      },
      "success": false,
      "steps": 310,
      "avg_latency_ms": 38.54
    },
    {
      "task_id": 9,
      "episode_idx": 4,
      "task_name": "open_the_middle_drawer_of_the_cabinet_table_2.bddl",
      "task_description": "open the middle drawer of the cabinet table 2",
      "perturb_info": {
        "base_suite": "open"
      },
      "success": false,
      "steps": 310,
      "avg_latency_ms": 38.32
    }
  ],
  "metadata": {
    "start_time": "2026-06-11T15:02:31.091710",
    "end_time": "2026-06-11T15:08:39.964186",
    "duration_seconds": 368.9,
    "hostname": "autodl-container-lezfbu0bdx-2f5bc1be"
  }
}